django_render_comments/__init__.py
django_render_comments/apps.py
django_render_comments/preprocessor.py
django_render_comments/py.typed
django_render_comments/loaders/__init__.py
django_render_comments/loaders/app_directories.py
django_render_comments/loaders/filesystem.py
django_render_comments-0.1.0.dist-info/METADATA
django_render_comments-0.1.0.dist-info/WHEEL
django_render_comments-0.1.0.dist-info/licenses/LICENSE.txt
django_render_comments-0.1.0.dist-info/RECORD
