Metadata-Version: 2.4
Name: django-render-comments
Version: 0.1.0
Summary: Reusable Django app for rendering Django template comments as HTML comments in DEBUG mode.
Project-URL: Homepage, https://github.com/sean-reed/django-render-comments
Project-URL: Repository, https://github.com/sean-reed/django-render-comments.git
Project-URL: Issues, https://github.com/sean-reed/django-render-comments/issues
Project-URL: Changelog, https://github.com/sean-reed/django-render-comments/releases
Author-email: Sean Reed <git@sean-reed.com>
License: MIT
License-File: LICENSE.txt
Keywords: comments,debugging,django,html,templates
Classifier: Development Status :: 4 - Beta
Classifier: Environment :: Web Environment
Classifier: Framework :: Django
Classifier: Framework :: Django :: 4.2
Classifier: Framework :: Django :: 5.0
Classifier: Framework :: Django :: 5.1
Classifier: Framework :: Django :: 5.2
Classifier: Framework :: Django :: 6.0
Classifier: Intended Audience :: Developers
Classifier: License :: OSI Approved :: MIT License
Classifier: Operating System :: OS Independent
Classifier: Programming Language :: Python :: 3
Classifier: Programming Language :: Python :: 3.10
Classifier: Programming Language :: Python :: 3.11
Classifier: Programming Language :: Python :: 3.12
Classifier: Programming Language :: Python :: 3.13
Classifier: Topic :: Internet :: WWW/HTTP
Classifier: Topic :: Software Development :: Libraries :: Python Modules
Requires-Python: >=3.10
Requires-Dist: django>=4.2
